{
  "title": "IMG_20180602_093604.jpg",
  "description": "",
  "url": "https://lh3.googleusercontent.com/-AFyV5TSmrs0/W2HVIyMWOdI/AAAAAAAAMX0/Q38rKu6suhkbWfXNgkREtSxyqy18hwRewCLABGAYYCw/s0-d/IMG_20180602_093604.jpg",
  "imageViews": "0",
  "creationTime": {
    "timestamp": "1533138210",
    "formatted": "Aug 1, 2018, 3:43:30 PM UTC"
  },
  "modificationTime": {
    "timestamp": "1533138210",
    "formatted": "Aug 1, 2018, 3:43:30 PM UTC"
  },
  "geoData": {
    "latitude": 13.520083333333334,
    "longitude": 99.95932222222223,
    "altitude": -35.55,
    "latitudeSpan": 0.0,
    "longitudeSpan": 0.0
  },
  "geoDataExif": {
    "latitude": 13.520083333333334,
    "longitude": 99.95932222222223,
    "altitude": -35.55,
    "latitudeSpan": 0.0,
    "longitudeSpan": 0.0
  },
  "photoTakenTime": {
    "timestamp": "1527906964",
    "formatted": "Jun 2, 2018, 2:36:04 AM UTC"
  }
}