{
  "title": "IMG_20180621_145132.jpg",
  "description": "",
  "url": "https://lh3.googleusercontent.com/-9oUiaXuKYEE/W2HVI6KGoTI/AAAAAAAAMX0/ZB6sj8C99iMAsp7UF8dX8cA5jtd8fhPFgCLABGAYYCw/s0-d/IMG_20180621_145132.jpg",
  "imageViews": "0",
  "creationTime": {
    "timestamp": "1533138210",
    "formatted": "Aug 1, 2018, 3:43:30 PM UTC"
  },
  "modificationTime": {
    "timestamp": "1533138210",
    "formatted": "Aug 1, 2018, 3:43:30 PM UTC"
  },
  "geoData": {
    "latitude": 21.02631111111111,
    "longitude": 105.85614722222222,
    "altitude": -31.93,
    "latitudeSpan": 0.0,
    "longitudeSpan": 0.0
  },
  "geoDataExif": {
    "latitude": 21.02631111111111,
    "longitude": 105.85614722222222,
    "altitude": -31.93,
    "latitudeSpan": 0.0,
    "longitudeSpan": 0.0
  },
  "photoTakenTime": {
    "timestamp": "1529567492",
    "formatted": "Jun 21, 2018, 7:51:32 AM UTC"
  }
}