{
  "title": "IMG_20180601_102514.jpg",
  "description": "",
  "url": "https://lh3.googleusercontent.com/-5uQJB8q5X5A/W2HVI0lwVFI/AAAAAAAAMX0/a4IX4eivtLYjOxYNWMiscnrNFKmEXrO_QCLABGAYYCw/s0-d/IMG_20180601_102514.jpg",
  "imageViews": "0",
  "creationTime": {
    "timestamp": "1533138210",
    "formatted": "Aug 1, 2018, 3:43:30 PM UTC"
  },
  "modificationTime": {
    "timestamp": "1533138210",
    "formatted": "Aug 1, 2018, 3:43:30 PM UTC"
  },
  "geoData": {
    "latitude": 13.719425,
    "longitude": 100.5128388888889,
    "altitude": -28.92,
    "latitudeSpan": 0.0,
    "longitudeSpan": 0.0
  },
  "geoDataExif": {
    "latitude": 13.719425,
    "longitude": 100.5128388888889,
    "altitude": -28.92,
    "latitudeSpan": 0.0,
    "longitudeSpan": 0.0
  },
  "photoTakenTime": {
    "timestamp": "1527823514",
    "formatted": "Jun 1, 2018, 3:25:14 AM UTC"
  }
}